_pybinding.cpython-314-darwin.so
pybinding/__about__.py
pybinding/__init__.py
pybinding/chebyshev.py
pybinding/constants.py
pybinding/greens.py
pybinding/lattice.py
pybinding/leads.py
pybinding/model.py
pybinding/modifier.py
pybinding/parallel.py
pybinding/pltutils.py
pybinding/results.py
pybinding/shape.py
pybinding/solver.py
pybinding/system.py
pybinding/repository/__init__.py
pybinding/repository/examples.py
pybinding/repository/group6_tmd.py
pybinding/repository/phosphorene.py
pybinding/repository/graphene/__init__.py
pybinding/repository/graphene/constants.py
pybinding/repository/graphene/lattice.py
pybinding/repository/graphene/modifiers.py
pybinding/repository/graphene/shape.py
pybinding/repository/graphene/utils.py
pybinding/support/__init__.py
pybinding/support/alias.py
pybinding/support/collections.py
pybinding/support/deprecated.py
pybinding/support/fuzzy_set.py
pybinding/support/inspect.py
pybinding/support/kwant.py
pybinding/support/pickle.py
pybinding/support/structure.py
pybinding/utils/__init__.py
pybinding/utils/cpuinfo.py
pybinding/utils/misc.py
pybinding/utils/progressbar.py
pybinding/utils/time.py
pybinding_hj-0.10.1.dist-info/METADATA
pybinding_hj-0.10.1.dist-info/WHEEL
pybinding_hj-0.10.1.dist-info/top_level.txt
pybinding_hj-0.10.1.dist-info/RECORD
