Metadata-Version: 2.4
Name: pybinding-hj
Version: 0.10.1
Summary: Modernized fork of pybinding - numerical tight-binding calculations with Python 3.14 and NumPy 2.x support
Author: HyangMin Jeong
Author-email: Dean Moldovan <dean0x7d@gmail.com>
Maintainer: HyangMin Jeong
License: BSD
Project-URL: Homepage, https://github.com/hyangminj/pybinding
Project-URL: Documentation, http://docs.pybinding.site/
Project-URL: Repository, https://github.com/hyangminj/pybinding
Project-URL: Issues, https://github.com/hyangminj/pybinding/issues
Project-URL: Upstream, https://github.com/dean0x7d/pybinding
Keywords: pybinding,tight-binding,solid-state,physics,cmt,condensed-matter
Classifier: Development Status :: 4 - Beta
Classifier: Intended Audience :: Science/Research
Classifier: Topic :: Scientific/Engineering :: Physics
Classifier: License :: OSI Approved :: BSD License
Classifier: Programming Language :: C++
Classifier: Programming Language :: Python :: 3 :: Only
Classifier: Programming Language :: Python :: 3.10
Classifier: Programming Language :: Python :: 3.11
Classifier: Programming Language :: Python :: 3.12
Classifier: Programming Language :: Python :: 3.13
Classifier: Programming Language :: Python :: Implementation :: CPython
Requires-Python: >=3.10
Requires-Dist: numpy>=1.20
Requires-Dist: scipy>=1.7
Requires-Dist: matplotlib>=3.3
Provides-Extra: dev
Requires-Dist: pytest>=6.0; extra == "dev"
Requires-Dist: pytest-cov; extra == "dev"
Requires-Dist: black>=22.0; extra == "dev"
Requires-Dist: mypy>=0.950; extra == "dev"
Requires-Dist: ruff>=0.1.0; extra == "dev"
Provides-Extra: mkl
Requires-Dist: mkl>=2021.0; extra == "mkl"
Provides-Extra: docs
Requires-Dist: sphinx>=4.0; extra == "docs"
Requires-Dist: sphinx-rtd-theme; extra == "docs"
Dynamic: requires-python
